{
 "cells": [
  {
   "cell_type": "code",
   "execution_count": 1,
   "id": "5c0f9655",
   "metadata": {},
   "outputs": [],
   "source": [
    "words = '''aback\tassay\tblurb\tchafe\tcraze\tdraft\tfaint\tfront\tguess\titchy\tlucky\tmusic\tperch\tqueer\trupee\tshrug\tsperm\tswear\ttrack\tvital\n",
    "abase\tasset\tblurt\tchaff\tcrazy\tdrain\tfairy\tfrost\tguest\tivory\tlumen\tmusky\tperil\tquell\trural\tshuck\tspice\tsweat\ttract\tvivid\n",
    "abate\tatoll\tblush\tchain\tcreak\tdrake\tfaith\tfroth\tguide\tjaunt\tlumpy\tmusty\tperky\tquery\trusty\tshunt\tspicy\tsweep\ttrade\tvixen\n",
    "abbey\tatone\tboard\tchair\tcream\tdrama\tfancy\tfrown\tguild\tjazzy\tlunar\tmyrrh\tpesky\tquest\tsadly\tshush\tspied\tsweet\ttrail\tvocal\n",
    "abbot\tattic\tboast\tchalk\tcredo\tdrank\tfanny\tfroze\tguile\tjelly\tlunch\tnadir\tpesto\tqueue\tsafer\tshyly\tspiel\tswell\ttrain\tvodka\n",
    "abhor\taudio\tbobby\tchamp\tcreed\tdrape\tfarce\tfruit\tguilt\tjerky\tlunge\tnaive\tpetal\tquick\tsaint\tsiege\tspike\tswept\ttrait\tvogue\n",
    "abide\taudit\tboney\tchant\tcreek\tdrawl\tfatal\tfudge\tguise\tjetty\tlupus\tnanny\tpetty\tquiet\tsalad\tsieve\tspiky\tswift\ttramp\tvoice\n",
    "abled\taugur\tbongo\tchaos\tcreep\tdrawn\tfatty\tfugue\tgulch\tjewel\tlurch\tnasal\tphase\tquill\tsally\tsight\tspill\tswill\ttrash\tvoila\n",
    "abode\taunty\tbonus\tchard\tcreme\tdread\tfault\tfully\tgully\tjiffy\tlurid\tnasty\tphone\tquilt\tsalon\tsigma\tspilt\tswine\ttrawl\tvomit\n",
    "abort\tavail\tbooby\tcharm\tcrepe\tdream\tfauna\tfungi\tgumbo\tjoint\tlusty\tnatal\tphony\tquirk\tsalsa\tsilky\tspine\tswing\ttread\tvoter\n",
    "about\tavert\tboost\tchart\tcrept\tdress\tfavor\tfunky\tgummy\tjoist\tlying\tnaval\tphoto\tquite\tsalty\tsilly\tspiny\tswirl\ttreat\tvouch\n",
    "above\tavian\tbooth\tchase\tcress\tdried\tfeast\tfunny\tguppy\tjoker\tlymph\tnavel\tpiano\tquota\tsalve\tsince\tspire\tswish\ttrend\tvowel\n",
    "abuse\tavoid\tbooty\tchasm\tcrest\tdrier\tfecal\tfuror\tgusto\tjolly\tlyric\tneedy\tpicky\tquote\tsalvo\tsinew\tspite\tswoon\ttriad\tvying\n",
    "abyss\tawait\tbooze\tcheap\tcrick\tdrift\tfeign\tfurry\tgusty\tjoust\tmacaw\tneigh\tpiece\tquoth\tsandy\tsinge\tsplat\tswoop\ttrial\twacky\n",
    "acorn\tawake\tboozy\tcheat\tcried\tdrill\tfella\tfussy\tgypsy\tjudge\tmacho\tnerdy\tpiety\trabbi\tsaner\tsiren\tsplit\tsword\ttribe\twafer\n",
    "acrid\taward\tborax\tcheck\tcrier\tdrink\tfelon\tfuzzy\thabit\tjuice\tmacro\tnerve\tpiggy\trabid\tsappy\tsissy\tspoil\tswore\ttrice\twager\n",
    "actor\taware\tborne\tcheek\tcrime\tdrive\tfemme\tgaffe\thairy\tjuicy\tmadam\tnever\tpilot\tracer\tsassy\tsixth\tspoke\tsworn\ttrick\twagon\n",
    "acute\tawash\tbosom\tcheer\tcrimp\tdroit\tfemur\tgaily\thalve\tjumbo\tmadly\tnewer\tpinch\tradar\tsatin\tsixty\tspoof\tswung\ttried\twaist\n",
    "adage\tawful\tbossy\tchess\tcrisp\tdroll\tfence\tgamer\thandy\tjumpy\tmafia\tnewly\tpiney\tradii\tsatyr\tskate\tspook\tsynod\ttripe\twaive\n",
    "adapt\tawoke\tbotch\tchest\tcroak\tdrone\tferal\tgamma\thappy\tjunta\tmagic\tnicer\tpinky\tradio\tsauce\tskier\tspool\tsyrup\ttrite\twaltz\n",
    "adept\taxial\tbough\tchick\tcrock\tdrool\tferry\tgamut\thardy\tjunto\tmagma\tniche\tpinto\trainy\tsaucy\tskiff\tspoon\ttabby\ttroll\twarty\n",
    "adieu\taxiom\tboule\tchide\tcrone\tdroop\tfetal\tgassy\tharem\tjuror\tmaize\tniece\tpiper\traise\tsauna\tskill\tspore\ttable\ttroop\twaste\n",
    "admin\taxion\tbound\tchief\tcrony\tdross\tfetch\tgaudy\tharpy\tkappa\tmajor\tnight\tpique\trajah\tsaute\tskimp\tsport\ttaboo\ttrope\twatch\n",
    "admit\tazure\tbowel\tchild\tcrook\tdrove\tfetid\tgauge\tharry\tkarma\tmaker\tninja\tpitch\trally\tsavor\tskirt\tspout\ttacit\ttrout\twater\n",
    "adobe\tbacon\tboxer\tchili\tcross\tdrown\tfetus\tgaunt\tharsh\tkayak\tmambo\tninny\tpithy\tralph\tsavoy\tskulk\tspray\ttacky\ttrove\twaver\n",
    "adopt\tbadge\tbrace\tchill\tcroup\tdruid\tfever\tgauze\thaste\tkebab\tmamma\tninth\tpivot\tramen\tsavvy\tskull\tspree\ttaffy\ttruce\twaxen\n",
    "adore\tbadly\tbraid\tchime\tcrowd\tdrunk\tfewer\tgavel\thasty\tkhaki\tmammy\tnoble\tpixel\tranch\tscald\tskunk\tsprig\ttaint\ttruck\tweary\n",
    "adorn\tbagel\tbrain\tchina\tcrown\tdryer\tfiber\tgawky\thatch\tkinky\tmanga\tnobly\tpixie\trandy\tscale\tslack\tspunk\ttaken\ttruer\tweave\n",
    "adult\tbaggy\tbrake\tchirp\tcrude\tdryly\tficus\tgayer\thater\tkiosk\tmange\tnoise\tpizza\trange\tscalp\tslain\tspurn\ttaker\ttruly\twedge\n",
    "affix\tbaker\tbrand\tchock\tcruel\tduchy\tfield\tgayly\thaunt\tkitty\tmango\tnoisy\tplace\trapid\tscaly\tslang\tspurt\ttally\ttrump\tweedy\n",
    "afire\tbaler\tbrash\tchoir\tcrumb\tdully\tfiend\tgazer\thaute\tknack\tmangy\tnomad\tplaid\trarer\tscamp\tslant\tsquad\ttalon\ttrunk\tweigh\n",
    "afoot\tbalmy\tbrass\tchoke\tcrump\tdummy\tfiery\tgecko\thaven\tknave\tmania\tnoose\tplain\traspy\tscant\tslash\tsquat\ttamer\ttruss\tweird\n",
    "afoul\tbanal\tbrave\tchord\tcrush\tdumpy\tfifth\tgeeky\thavoc\tknead\tmanic\tnorth\tplait\tratio\tscare\tslate\tsquib\ttango\ttrust\twelch\n",
    "after\tbanjo\tbravo\tchore\tcrust\tdunce\tfifty\tgeese\thazel\tkneed\tmanly\tnosey\tplane\tratty\tscarf\tsleek\tstack\ttangy\ttruth\twelsh\n",
    "again\tbarge\tbrawl\tchose\tcrypt\tdusky\tfight\tgenie\theady\tkneel\tmanor\tnotch\tplank\traven\tscary\tsleep\tstaff\ttaper\ttryst\twhack\n",
    "agape\tbaron\tbrawn\tchuck\tcubic\tdusty\tfiler\tgenre\theard\tknelt\tmaple\tnovel\tplant\trayon\tscene\tsleet\tstage\ttapir\ttubal\twhale\n",
    "agate\tbasal\tbread\tchump\tcumin\tdutch\tfilet\tghost\theart\tknife\tmarch\tnudge\tplate\trazor\tscent\tslept\tstaid\ttardy\ttuber\twharf\n",
    "agent\tbasic\tbreak\tchunk\tcurio\tduvet\tfilly\tghoul\theath\tknock\tmarry\tnurse\tplaza\treach\tscion\tslice\tstain\ttarot\ttulip\twheat\n",
    "agile\tbasil\tbreed\tchurn\tcurly\tdwarf\tfilmy\tgiant\theave\tknoll\tmarsh\tnutty\tplead\treact\tscoff\tslick\tstair\ttaste\ttulle\twheel\n",
    "aging\tbasin\tbriar\tchute\tcurry\tdwell\tfilth\tgiddy\theavy\tknown\tmason\tnylon\tpleat\tready\tscold\tslide\tstake\ttasty\ttumor\twhelp\n",
    "aglow\tbasis\tbribe\tcider\tcurse\tdwelt\tfinal\tgipsy\thedge\tkoala\tmasse\tnymph\tplied\trealm\tscone\tslime\tstale\ttatty\ttunic\twhere\n",
    "agony\tbaste\tbrick\tcigar\tcurve\tdying\tfinch\tgirly\thefty\tkrill\tmatch\toaken\tplier\trearm\tscoop\tslimy\tstalk\ttaunt\tturbo\twhich\n",
    "agree\tbatch\tbride\tcinch\tcurvy\teager\tfiner\tgirth\theist\tlabel\tmatey\tobese\tpluck\trebar\tscope\tsling\tstall\ttawny\ttutor\twhiff\n",
    "ahead\tbathe\tbrief\tcirca\tcutie\teagle\tfirst\tgiven\thelix\tlabor\tmauve\toccur\tplumb\trebel\tscore\tslink\tstamp\tteach\ttwang\twhile\n",
    "aider\tbaton\tbrine\tcivic\tcyber\tearly\tfishy\tgiver\thello\tladen\tmaxim\tocean\tplume\trebus\tscorn\tsloop\tstand\tteary\ttweak\twhine\n",
    "aisle\tbatty\tbring\tcivil\tcycle\tearth\tfixer\tglade\thence\tladle\tmaybe\toctal\tplump\trebut\tscour\tslope\tstank\ttease\ttweed\twhiny\n",
    "alarm\tbawdy\tbrink\tclack\tcynic\teasel\tfizzy\tgland\theron\tlager\tmayor\toctet\tplunk\trecap\tscout\tslosh\tstare\tteddy\ttweet\twhirl\n",
    "album\tbayou\tbriny\tclaim\tdaddy\teaten\tfjord\tglare\thilly\tlance\tmealy\todder\tplush\trecur\tscowl\tsloth\tstark\tteeth\ttwice\twhisk\n",
    "alert\tbeach\tbrisk\tclamp\tdaily\teater\tflack\tglass\thinge\tlanky\tmeant\toddly\tpoesy\trecut\tscram\tslump\tstart\ttempo\ttwine\twhite\n",
    "algae\tbeady\tbroad\tclang\tdairy\tebony\tflail\tglaze\thippo\tlapel\tmeaty\toffal\tpoint\treedy\tscrap\tslung\tstash\ttenet\ttwirl\twhole\n",
    "alibi\tbeard\tbroil\tclank\tdaisy\teclat\tflair\tgleam\thippy\tlapse\tmecca\toffer\tpoise\trefer\tscree\tslunk\tstate\ttenor\ttwist\twhoop\n",
    "alien\tbeast\tbroke\tclash\tdally\tedict\tflake\tglean\thitch\tlarge\tmedal\toften\tpoker\trefit\tscrew\tslurp\tstave\ttense\ttwixt\twhose\n",
    "align\tbeech\tbrood\tclasp\tdance\tedify\tflaky\tglide\thoard\tlarva\tmedia\tolden\tpolar\tregal\tscrub\tslush\tstead\ttenth\ttying\twiden\n",
    "alike\tbeefy\tbrook\tclass\tdandy\teerie\tflame\tglint\thobby\tlasso\tmedic\tolder\tpolka\trehab\tscrum\tslyly\tsteak\ttepee\tudder\twider\n",
    "alive\tbefit\tbroom\tclean\tdatum\tegret\tflank\tgloat\thoist\tlatch\tmelee\tolive\tpolyp\treign\tscuba\tsmack\tsteal\ttepid\tulcer\twidow\n",
    "allay\tbegan\tbroth\tclear\tdaunt\teight\tflare\tglobe\tholly\tlater\tmelon\tombre\tpooch\trelax\tsedan\tsmall\tsteam\tterra\tultra\twidth\n",
    "alley\tbegat\tbrown\tcleat\tdealt\teject\tflash\tgloom\thomer\tlathe\tmends\tomega\tpoppy\trelay\tseedy\tsmart\tsteed\tterse\tumbra\twield\n",
    "allot\tbeget\tbrunt\tcleft\tdeath\teking\tflask\tglory\thoney\tlatte\tmercy\tonion\tporch\trelic\tsegue\tsmash\tsteel\ttesty\tuncle\twight\n",
    "allow\tbegin\tbrush\tclerk\tdebar\telate\tfleck\tgloss\thonor\tlaugh\tmerge\tonset\tposer\tremit\tseize\tsmear\tsteep\tthank\tuncut\twilly\n",
    "alloy\tbegun\tbrute\tclick\tdebit\telbow\tfleet\tglove\thorde\tlayer\tmerit\topera\tposit\trenal\tsemen\tsmell\tsteer\ttheft\tunder\twimpy\n",
    "aloft\tbeing\tbuddy\tcliff\tdebug\telder\tflesh\tglyph\thorny\tleach\tmerry\topine\tposse\trenew\tsense\tsmelt\tstein\ttheir\tundid\twince\n",
    "alone\tbelch\tbudge\tclimb\tdebut\telect\tflick\tgnash\thorse\tleafy\tmetal\topium\tpouch\trepay\tsepia\tsmile\tstern\ttheme\tundue\twinch\n",
    "along\tbelie\tbuggy\tcling\tdecal\telegy\tflier\tgnome\thotel\tleaky\tmeter\toptic\tpound\trepel\tserif\tsmirk\tstick\tthere\tunfed\twindy\n",
    "aloof\tbelle\tbugle\tclink\tdecay\telfin\tfling\tgodly\thotly\tleant\tmetro\torbit\tpouty\treply\tserum\tsmite\tstiff\tthese\tunfit\twiser\n",
    "aloud\tbelly\tbuild\tcloak\tdecor\telide\tflint\tgoing\thound\tleapt\tmicro\torder\tpower\trerun\tserve\tsmith\tstill\ttheta\tunify\twispy\n",
    "alpha\tbelow\tbuilt\tclock\tdecoy\telite\tflirt\tgolem\thouse\tlearn\tmidge\torgan\tprank\treset\tsetup\tsmock\tstilt\tthick\tunion\twitch\n",
    "altar\tbench\tbulge\tclone\tdecry\telope\tfloat\tgolly\thovel\tlease\tmidst\tother\tprawn\tresin\tseven\tsmoke\tsting\tthief\tunite\twitty\n",
    "alter\tberet\tbulky\tclose\tdefer\telude\tflock\tgonad\thover\tleash\tmight\totter\tpreen\tretch\tsever\tsmoky\tstink\tthigh\tunity\twoken\n",
    "amass\tberry\tbully\tcloth\tdeign\temail\tflood\tgoner\thowdy\tleast\tmilky\tought\tpress\tretro\tsewer\tsmote\tstint\tthing\tunlit\twoman\n",
    "amaze\tberth\tbunch\tcloud\tdeity\tembed\tfloor\tgoody\thuman\tleave\tmimic\tounce\tprice\tretry\tshack\tsnack\tstock\tthink\tunmet\twomen\n",
    "amber\tbeset\tbunny\tclout\tdelay\tember\tflora\tgooey\thumid\tledge\tmince\toutdo\tprick\treuse\tshade\tsnail\tstoic\tthird\tunset\twoody\n",
    "amble\tbetel\tburly\tclove\tdelta\temcee\tfloss\tgoofy\thumor\tleech\tminer\touter\tpride\trevel\tshady\tsnake\tstoke\tthong\tuntie\twooer\n",
    "amend\tbevel\tburnt\tclown\tdelve\tempty\tflour\tgoose\thumph\tleery\tminim\toutgo\tpried\trevue\tshaft\tsnaky\tstole\tthorn\tuntil\twooly\n",
    "amiss\tbezel\tburst\tcluck\tdemon\tenact\tflout\tgorge\thumus\tlefty\tminor\tovary\tprime\trhino\tshake\tsnare\tstomp\tthose\tunwed\twoozy\n",
    "amity\tbible\tbused\tclued\tdemur\tendow\tflown\tgouge\thunch\tlegal\tminty\tovate\tprimo\trhyme\tshaky\tsnarl\tstone\tthree\tunzip\twordy\n",
    "among\tbicep\tbushy\tclump\tdenim\tenema\tfluff\tgourd\thunky\tleggy\tminus\tovert\tprint\trider\tshale\tsneak\tstony\tthrew\tupper\tworld\n",
    "ample\tbiddy\tbutch\tclung\tdense\tenemy\tfluid\tgrace\thurry\tlemon\tmirth\tovine\tprior\tridge\tshall\tsneer\tstood\tthrob\tupset\tworry\n",
    "amply\tbigot\tbutte\tcoach\tdepot\tenjoy\tfluke\tgrade\thusky\tlemur\tmiser\tovoid\tprism\trifle\tshalt\tsnide\tstool\tthrow\turban\tworse\n",
    "amuse\tbilge\tbuxom\tcoast\tdepth\tennui\tflume\tgraft\thussy\tleper\tmissy\towing\tprivy\tright\tshame\tsniff\tstoop\tthrum\turine\tworst\n",
    "angel\tbilly\tbuyer\tcobra\tderby\tensue\tflung\tgrail\thutch\tlevel\tmocha\towner\tprize\trigid\tshank\tsnipe\tstore\tthumb\tusage\tworth\n",
    "anger\tbinge\tbylaw\tcocoa\tdeter\tenter\tflunk\tgrain\thydro\tlever\tmodal\toxide\tprobe\trigor\tshape\tsnoop\tstork\tthump\tusher\twould\n",
    "angle\tbingo\tcabal\tcolon\tdetox\tentry\tflush\tgrand\thyena\tlibel\tmodel\tozone\tprone\trinse\tshard\tsnore\tstorm\tthyme\tusing\twound\n",
    "angry\tbiome\tcabby\tcolor\tdeuce\tenvoy\tflute\tgrant\thymen\tliege\tmodem\tpaddy\tprong\tripen\tshare\tsnort\tstory\ttiara\tusual\twoven\n",
    "angst\tbirch\tcabin\tcomet\tdevil\tepoch\tflyer\tgrape\thyper\tlight\tmogul\tpagan\tproof\triper\tshark\tsnout\tstout\ttibia\tusurp\twrack\n",
    "anime\tbirth\tcable\tcomfy\tdiary\tepoxy\tfoamy\tgraph\ticily\tliken\tmoist\tpaint\tprose\trisen\tsharp\tsnowy\tstove\ttidal\tutile\twrath\n",
    "ankle\tbison\tcacao\tcomic\tdicey\tequal\tfocal\tgrasp\ticing\tlilac\tmolar\tpaler\tproud\triser\tshave\tsnuck\tstrap\ttiger\tutter\twreak\n",
    "annex\tbitty\tcache\tcomma\tdigit\tequip\tfocus\tgrass\tideal\tlimbo\tmoldy\tpalsy\tprove\trisky\tshawl\tsnuff\tstraw\ttight\tvague\twreck\n",
    "annoy\tblack\tcacti\tconch\tdilly\terase\tfoggy\tgrate\tidiom\tlimit\tmoney\tpanel\tprowl\trival\tshear\tsoapy\tstray\ttilde\tvalet\twrest\n",
    "annul\tblade\tcaddy\tcondo\tdimly\terect\tfoist\tgrave\tidiot\tlinen\tmonth\tpanic\tproxy\triver\tsheen\tsober\tstrip\ttimer\tvalid\twring\n",
    "anode\tblame\tcadet\tconic\tdiner\terode\tfolio\tgravy\tidler\tliner\tmoody\tpansy\tprude\trivet\tsheep\tsoggy\tstrut\ttimid\tvalor\twrist\n",
    "antic\tbland\tcagey\tcopse\tdingo\terror\tfolly\tgraze\tidyll\tlingo\tmoose\tpapal\tprune\troach\tsheer\tsolar\tstuck\ttipsy\tvalue\twrite\n",
    "anvil\tblank\tcairn\tcoral\tdingy\terupt\tforay\tgreat\tigloo\tlipid\tmoral\tpaper\tpsalm\troast\tsheet\tsolid\tstudy\ttitan\tvalve\twrong\n",
    "aorta\tblare\tcamel\tcorer\tdiode\tessay\tforce\tgreed\tiliac\tlithe\tmoron\tparer\tpubic\trobin\tsheik\tsolve\tstuff\ttithe\tvapid\twrote\n",
    "apart\tblast\tcameo\tcorny\tdirge\tester\tforge\tgreen\timage\tliver\tmorph\tparka\tpudgy\trobot\tshelf\tsonar\tstump\ttitle\tvapor\twrung\n",
    "aphid\tblaze\tcanal\tcouch\tdirty\tether\tforgo\tgreet\timbue\tlivid\tmossy\tparry\tpuffy\trocky\tshell\tsonic\tstung\ttoast\tvault\twryly\n",
    "aping\tbleak\tcandy\tcough\tdisco\tethic\tforte\tgrief\timpel\tllama\tmotel\tparse\tpulpy\trodeo\tshied\tsooth\tstunk\ttoday\tvaunt\tyacht\n",
    "apnea\tbleat\tcanny\tcould\tditch\tethos\tforth\tgrill\timply\tloamy\tmotif\tparty\tpulse\troger\tshift\tsooty\tstunt\ttoddy\tvegan\tyearn\n",
    "apple\tbleed\tcanoe\tcount\tditto\tetude\tforty\tgrime\tinane\tloath\tmotor\tpasta\tpunch\trogue\tshine\tsorry\tstyle\ttoken\tvenom\tyeast\n",
    "apply\tbleep\tcanon\tcoupe\tditty\tevade\tforum\tgrimy\tinbox\tlobby\tmotto\tpaste\tpupil\troomy\tshiny\tsound\tsuave\ttonal\tvenue\tyield\n",
    "apron\tblend\tcaper\tcourt\tdiver\tevent\tfound\tgrind\tincur\tlocal\tmoult\tpasty\tpuppy\troost\tshire\tsouth\tsugar\ttonga\tverge\tyoung\n",
    "aptly\tbless\tcaput\tcoven\tdizzy\tevery\tfoyer\tgripe\tindex\tlocus\tmound\tpatch\tpuree\trotor\tshirk\tsower\tsuing\ttonic\tverse\tyouth\n",
    "arbor\tblimp\tcarat\tcover\tdodge\tevict\tfrail\tgroan\tinept\tlodge\tmount\tpatio\tpurer\trouge\tshirt\tspace\tsuite\ttooth\tverso\tzebra\n",
    "ardor\tblind\tcargo\tcovet\tdodgy\tevoke\tframe\tgroin\tinert\tlofty\tmourn\tpatsy\tpurge\trough\tshoal\tspade\tsulky\ttopaz\tverve\tzesty\n",
    "arena\tblink\tcarol\tcovey\tdogma\texact\tfrank\tgroom\tinfer\tlogic\tmouse\tpatty\tpurse\tround\tshock\tspank\tsully\ttopic\tvicar\tzonal\n",
    "argue\tbliss\tcarry\tcower\tdoing\texalt\tfraud\tgrope\tingot\tlogin\tmouth\tpause\tpushy\trouse\tshone\tspare\tsumac\ttorch\tvideo\t \n",
    "arise\tblitz\tcarve\tcoyly\tdolly\texcel\tfreak\tgross\tinlay\tloopy\tmover\tpayee\tputty\troute\tshook\tspark\tsunny\ttorso\tvigil\t \n",
    "armor\tbloat\tcaste\tcrack\tdonor\texert\tfreed\tgroup\tinlet\tloose\tmovie\tpayer\tpygmy\trover\tshoot\tspasm\tsuper\ttorus\tvigor\t \n",
    "aroma\tblock\tcatch\tcraft\tdonut\texile\tfreer\tgrout\tinner\tlorry\tmower\tpeace\tquack\trowdy\tshore\tspawn\tsurer\ttotal\tvilla\t \n",
    "arose\tbloke\tcater\tcramp\tdopey\texist\tfresh\tgrove\tinput\tloser\tmucky\tpeach\tquail\trower\tshorn\tspeak\tsurge\ttotem\tvinyl\t \n",
    "array\tblond\tcatty\tcrane\tdoubt\texpel\tfriar\tgrowl\tinter\tlouse\tmucus\tpearl\tquake\troyal\tshort\tspear\tsurly\ttouch\tviola\t \n",
    "arrow\tblood\tcaulk\tcrank\tdough\textol\tfried\tgrown\tintro\tlousy\tmuddy\tpecan\tqualm\truddy\tshout\tspeck\tsushi\ttough\tviper\t \n",
    "arson\tbloom\tcause\tcrash\tdowdy\textra\tfrill\tgruel\tionic\tlover\tmulch\tpedal\tquark\truder\tshove\tspeed\tswami\ttowel\tviral\t \n",
    "artsy\tblown\tcavil\tcrass\tdowel\texult\tfrisk\tgruff\tirate\tlower\tmummy\tpenal\tquart\trugby\tshown\tspell\tswamp\ttower\tvirus\t \n",
    "ascot\tbluer\tcease\tcrate\tdowny\teying\tfritz\tgrunt\tirony\tlowly\tmunch\tpence\tquash\truler\tshowy\tspelt\tswarm\ttoxic\tvisit\t \n",
    "ashen\tbluff\tcedar\tcrave\tdowry\tfable\tfrock\tguard\tislet\tloyal\tmural\tpenne\tquasi\trumba\tshrew\tspend\tswash\ttoxin\tvisor\t \n",
    "aside\tblunt\tcello\tcrawl\tdozen\tfacet\tfrond\tguava\tissue\tlucid\tmurky\tpenny\tqueen\trumor\tshrub\tspent\tswath\ttrace\tvista\t \n",
    "askew\t \t \t \t \t \t \t \t \t \tmushy'''\n",
    "words = '\t'.join([line for line in words.split('\\n')])\n",
    "words = [word.strip() for word in words.strip().split('\t') if len(word) == 5]"
   ]
  },
  {
   "cell_type": "code",
   "execution_count": 2,
   "id": "1a8f4fad",
   "metadata": {},
   "outputs": [
    {
     "name": "stdout",
     "output_type": "stream",
     "text": [
      "['which']\n"
     ]
    }
   ],
   "source": [
    "def wordle(guesses: list[str], green: dict, yellow: dict) -> list[str]:\n",
    "    import re\n",
    "    \n",
    "    chars = set('abcdefghijklmnopqrstuvwxyz')\n",
    "\n",
    "    for g in guesses:\n",
    "        chars -= set(g)\n",
    "    \n",
    "\n",
    "    \n",
    "    remaining_letters = ''\n",
    "    for c in chars:\n",
    "        remaining_letters += c\n",
    "        \n",
    "    remaining_letters += ''.join([str(value) for value in green.values()])\n",
    "    if yellow:\n",
    "        yellow_letters = set()\n",
    "        for value_list in yellow.values():\n",
    "            for v in value_list:\n",
    "                yellow_letters.add(v)\n",
    "        remaining_letters += ''.join([str(c) for c in yellow_letters])####\n",
    "\n",
    "    pattern = fr'[{remaining_letters}]{{5}}'\n",
    "    finder = re.compile(pattern)\n",
    "    \n",
    "    filtr = [w for w in words if \n",
    "                    all(w[key] == value for key, value in green.items())\n",
    "                   and finder.match(w)]\n",
    "    if yellow:\n",
    "        for item in yellow.items():\n",
    "            filtr = [w for w in filtr if all(w[item[0]] != value for value in item[1])]\n",
    "\n",
    "        filtr = [w for w in filtr if all(c in w for c in yellow_letters)]\n",
    "        \n",
    "    \n",
    "    \n",
    "    return filtr\n",
    "    \n",
    "guesses = ['alive','shirk', 'thing']\n",
    "green = {1:'h', 2:'i'}\n",
    "yellow = {0: 'c'}\n",
    "\n",
    "print(wordle(guesses, green = green, yellow = yellow))"
   ]
  },
  {
   "cell_type": "code",
   "execution_count": 4,
   "id": "458d027d",
   "metadata": {},
   "outputs": [
    {
     "name": "stdout",
     "output_type": "stream",
     "text": [
      "  2           0 LOAD_CONST               1 (0)\n",
      "              2 LOAD_CONST               0 (None)\n",
      "              4 IMPORT_NAME              0 (re)\n",
      "              6 STORE_FAST               3 (re)\n",
      "\n",
      "  4           8 LOAD_GLOBAL              1 (set)\n",
      "             10 LOAD_CONST               2 ('abcdefghijklmnopqrstuvwxyz')\n",
      "             12 CALL_FUNCTION            1\n",
      "             14 STORE_FAST               4 (chars)\n",
      "\n",
      "  6          16 LOAD_FAST                0 (guesses)\n",
      "             18 GET_ITER\n",
      "        >>   20 FOR_ITER                16 (to 38)\n",
      "             22 STORE_FAST               5 (g)\n",
      "\n",
      "  7          24 LOAD_FAST                4 (chars)\n",
      "             26 LOAD_GLOBAL              1 (set)\n",
      "             28 LOAD_FAST                5 (g)\n",
      "             30 CALL_FUNCTION            1\n",
      "             32 INPLACE_SUBTRACT\n",
      "             34 STORE_FAST               4 (chars)\n",
      "             36 JUMP_ABSOLUTE           20\n",
      "\n",
      " 11     >>   38 LOAD_CONST               3 ('')\n",
      "             40 STORE_FAST               6 (remaining_letters)\n",
      "\n",
      " 12          42 LOAD_FAST                4 (chars)\n",
      "             44 GET_ITER\n",
      "        >>   46 FOR_ITER                12 (to 60)\n",
      "             48 STORE_FAST               7 (c)\n",
      "\n",
      " 13          50 LOAD_FAST                6 (remaining_letters)\n",
      "             52 LOAD_FAST                7 (c)\n",
      "             54 INPLACE_ADD\n",
      "             56 STORE_FAST               6 (remaining_letters)\n",
      "             58 JUMP_ABSOLUTE           46\n",
      "\n",
      " 15     >>   60 LOAD_FAST                6 (remaining_letters)\n",
      "             62 LOAD_CONST               3 ('')\n",
      "             64 LOAD_METHOD              2 (join)\n",
      "             66 LOAD_CONST               4 (<code object <listcomp> at 0x7ffe14a7cbe0, file \"/var/folders/h4/77l8l2bd37z5_jkwbw_75nsw0000gn/T/ipykernel_4195/3792770386.py\", line 15>)\n",
      "             68 LOAD_CONST               5 ('wordle.<locals>.<listcomp>')\n",
      "             70 MAKE_FUNCTION            0\n",
      "             72 LOAD_DEREF               1 (green)\n",
      "             74 LOAD_METHOD              3 (values)\n",
      "             76 CALL_METHOD              0\n",
      "             78 GET_ITER\n",
      "             80 CALL_FUNCTION            1\n",
      "             82 CALL_METHOD              1\n",
      "             84 INPLACE_ADD\n",
      "             86 STORE_FAST               6 (remaining_letters)\n",
      "\n",
      " 16          88 LOAD_FAST                2 (yellow)\n",
      "             90 POP_JUMP_IF_FALSE      156\n",
      "\n",
      " 17          92 LOAD_GLOBAL              1 (set)\n",
      "             94 CALL_FUNCTION            0\n",
      "             96 STORE_DEREF              3 (yellow_letters)\n",
      "\n",
      " 18          98 LOAD_FAST                2 (yellow)\n",
      "            100 LOAD_METHOD              3 (values)\n",
      "            102 CALL_METHOD              0\n",
      "            104 GET_ITER\n",
      "        >>  106 FOR_ITER                24 (to 132)\n",
      "            108 STORE_FAST               8 (value_list)\n",
      "\n",
      " 19         110 LOAD_FAST                8 (value_list)\n",
      "            112 GET_ITER\n",
      "        >>  114 FOR_ITER                14 (to 130)\n",
      "            116 STORE_FAST               9 (v)\n",
      "\n",
      " 20         118 LOAD_DEREF               3 (yellow_letters)\n",
      "            120 LOAD_METHOD              4 (add)\n",
      "            122 LOAD_FAST                9 (v)\n",
      "            124 CALL_METHOD              1\n",
      "            126 POP_TOP\n",
      "            128 JUMP_ABSOLUTE          114\n",
      "        >>  130 JUMP_ABSOLUTE          106\n",
      "\n",
      " 21     >>  132 LOAD_FAST                6 (remaining_letters)\n",
      "            134 LOAD_CONST               3 ('')\n",
      "            136 LOAD_METHOD              2 (join)\n",
      "            138 LOAD_CONST               6 (<code object <listcomp> at 0x7ffe14a7cf50, file \"/var/folders/h4/77l8l2bd37z5_jkwbw_75nsw0000gn/T/ipykernel_4195/3792770386.py\", line 21>)\n",
      "            140 LOAD_CONST               5 ('wordle.<locals>.<listcomp>')\n",
      "            142 MAKE_FUNCTION            0\n",
      "            144 LOAD_DEREF               3 (yellow_letters)\n",
      "            146 GET_ITER\n",
      "            148 CALL_FUNCTION            1\n",
      "            150 CALL_METHOD              1\n",
      "            152 INPLACE_ADD\n",
      "            154 STORE_FAST               6 (remaining_letters)\n",
      "\n",
      " 23     >>  156 LOAD_CONST               7 ('[')\n",
      "            158 LOAD_FAST                6 (remaining_letters)\n",
      "            160 FORMAT_VALUE             0\n",
      "            162 LOAD_CONST               8 (']{5}')\n",
      "            164 BUILD_STRING             3\n",
      "            166 STORE_FAST              10 (pattern)\n",
      "\n",
      " 24         168 LOAD_FAST                3 (re)\n",
      "            170 LOAD_METHOD              5 (compile)\n",
      "            172 LOAD_FAST               10 (pattern)\n",
      "            174 CALL_METHOD              1\n",
      "            176 STORE_DEREF              0 (finder)\n",
      "\n",
      " 26         178 LOAD_CLOSURE             0 (finder)\n",
      "            180 LOAD_CLOSURE             1 (green)\n",
      "            182 BUILD_TUPLE              2\n",
      "            184 LOAD_CONST               9 (<code object <listcomp> at 0x7ffe14a923a0, file \"/var/folders/h4/77l8l2bd37z5_jkwbw_75nsw0000gn/T/ipykernel_4195/3792770386.py\", line 26>)\n",
      "            186 LOAD_CONST               5 ('wordle.<locals>.<listcomp>')\n",
      "            188 MAKE_FUNCTION            8 (closure)\n",
      "            190 LOAD_GLOBAL              6 (words)\n",
      "            192 GET_ITER\n",
      "            194 CALL_FUNCTION            1\n",
      "            196 STORE_FAST              11 (filtr)\n",
      "\n",
      " 29         198 LOAD_FAST                2 (yellow)\n",
      "            200 POP_JUMP_IF_FALSE      252\n",
      "\n",
      " 30         202 LOAD_FAST                2 (yellow)\n",
      "            204 LOAD_METHOD              7 (items)\n",
      "            206 CALL_METHOD              0\n",
      "            208 GET_ITER\n",
      "        >>  210 FOR_ITER                22 (to 234)\n",
      "            212 STORE_DEREF              2 (item)\n",
      "\n",
      " 31         214 LOAD_CLOSURE             2 (item)\n",
      "            216 BUILD_TUPLE              1\n",
      "            218 LOAD_CONST              10 (<code object <listcomp> at 0x7ffe14a92500, file \"/var/folders/h4/77l8l2bd37z5_jkwbw_75nsw0000gn/T/ipykernel_4195/3792770386.py\", line 31>)\n",
      "            220 LOAD_CONST               5 ('wordle.<locals>.<listcomp>')\n",
      "            222 MAKE_FUNCTION            8 (closure)\n",
      "            224 LOAD_FAST               11 (filtr)\n",
      "            226 GET_ITER\n",
      "            228 CALL_FUNCTION            1\n",
      "            230 STORE_FAST              11 (filtr)\n",
      "            232 JUMP_ABSOLUTE          210\n",
      "\n",
      " 33     >>  234 LOAD_CLOSURE             3 (yellow_letters)\n",
      "            236 BUILD_TUPLE              1\n",
      "            238 LOAD_CONST              11 (<code object <listcomp> at 0x7ffe14a920e0, file \"/var/folders/h4/77l8l2bd37z5_jkwbw_75nsw0000gn/T/ipykernel_4195/3792770386.py\", line 33>)\n",
      "            240 LOAD_CONST               5 ('wordle.<locals>.<listcomp>')\n",
      "            242 MAKE_FUNCTION            8 (closure)\n",
      "            244 LOAD_FAST               11 (filtr)\n",
      "            246 GET_ITER\n",
      "            248 CALL_FUNCTION            1\n",
      "            250 STORE_FAST              11 (filtr)\n",
      "\n",
      " 37     >>  252 LOAD_FAST               11 (filtr)\n",
      "            254 RETURN_VALUE\n",
      "\n",
      "Disassembly of <code object <listcomp> at 0x7ffe14a7cbe0, file \"/var/folders/h4/77l8l2bd37z5_jkwbw_75nsw0000gn/T/ipykernel_4195/3792770386.py\", line 15>:\n",
      " 15           0 BUILD_LIST               0\n",
      "              2 LOAD_FAST                0 (.0)\n",
      "        >>    4 FOR_ITER                12 (to 18)\n",
      "              6 STORE_FAST               1 (value)\n",
      "              8 LOAD_GLOBAL              0 (str)\n",
      "             10 LOAD_FAST                1 (value)\n",
      "             12 CALL_FUNCTION            1\n",
      "             14 LIST_APPEND              2\n",
      "             16 JUMP_ABSOLUTE            4\n",
      "        >>   18 RETURN_VALUE\n",
      "\n",
      "Disassembly of <code object <listcomp> at 0x7ffe14a7cf50, file \"/var/folders/h4/77l8l2bd37z5_jkwbw_75nsw0000gn/T/ipykernel_4195/3792770386.py\", line 21>:\n",
      " 21           0 BUILD_LIST               0\n",
      "              2 LOAD_FAST                0 (.0)\n",
      "        >>    4 FOR_ITER                12 (to 18)\n",
      "              6 STORE_FAST               1 (c)\n",
      "              8 LOAD_GLOBAL              0 (str)\n",
      "             10 LOAD_FAST                1 (c)\n",
      "             12 CALL_FUNCTION            1\n",
      "             14 LIST_APPEND              2\n",
      "             16 JUMP_ABSOLUTE            4\n",
      "        >>   18 RETURN_VALUE\n",
      "\n",
      "Disassembly of <code object <listcomp> at 0x7ffe14a923a0, file \"/var/folders/h4/77l8l2bd37z5_jkwbw_75nsw0000gn/T/ipykernel_4195/3792770386.py\", line 26>:\n",
      " 26           0 BUILD_LIST               0\n",
      "              2 LOAD_FAST                0 (.0)\n",
      "        >>    4 FOR_ITER                44 (to 50)\n",
      "              6 STORE_DEREF              0 (w)\n",
      "\n",
      " 27           8 LOAD_GLOBAL              0 (all)\n",
      "             10 LOAD_CLOSURE             0 (w)\n",
      "             12 BUILD_TUPLE              1\n",
      "             14 LOAD_CONST               0 (<code object <genexpr> at 0x7ffe14a922f0, file \"/var/folders/h4/77l8l2bd37z5_jkwbw_75nsw0000gn/T/ipykernel_4195/3792770386.py\", line 27>)\n",
      "             16 LOAD_CONST               1 ('wordle.<locals>.<listcomp>.<genexpr>')\n",
      "             18 MAKE_FUNCTION            8 (closure)\n",
      "             20 LOAD_DEREF               2 (green)\n",
      "             22 LOAD_METHOD              1 (items)\n",
      "             24 CALL_METHOD              0\n",
      "             26 GET_ITER\n",
      "             28 CALL_FUNCTION            1\n",
      "             30 CALL_FUNCTION            1\n",
      "             32 POP_JUMP_IF_FALSE        4\n",
      "\n",
      " 28          34 LOAD_DEREF               1 (finder)\n",
      "             36 LOAD_METHOD              2 (match)\n",
      "             38 LOAD_DEREF               0 (w)\n",
      "             40 CALL_METHOD              1\n",
      "             42 POP_JUMP_IF_FALSE        4\n",
      "\n",
      " 26          44 LOAD_DEREF               0 (w)\n",
      "             46 LIST_APPEND              2\n",
      "             48 JUMP_ABSOLUTE            4\n",
      "        >>   50 RETURN_VALUE\n",
      "\n",
      "Disassembly of <code object <genexpr> at 0x7ffe14a922f0, file \"/var/folders/h4/77l8l2bd37z5_jkwbw_75nsw0000gn/T/ipykernel_4195/3792770386.py\", line 27>:\n",
      " 27           0 LOAD_FAST                0 (.0)\n",
      "        >>    2 FOR_ITER                22 (to 26)\n",
      "              4 UNPACK_SEQUENCE          2\n",
      "              6 STORE_FAST               1 (key)\n",
      "              8 STORE_FAST               2 (value)\n",
      "             10 LOAD_DEREF               0 (w)\n",
      "             12 LOAD_FAST                1 (key)\n",
      "             14 BINARY_SUBSCR\n",
      "             16 LOAD_FAST                2 (value)\n",
      "             18 COMPARE_OP               2 (==)\n",
      "             20 YIELD_VALUE\n",
      "             22 POP_TOP\n",
      "             24 JUMP_ABSOLUTE            2\n",
      "        >>   26 LOAD_CONST               0 (None)\n",
      "             28 RETURN_VALUE\n",
      "\n",
      "Disassembly of <code object <listcomp> at 0x7ffe14a92500, file \"/var/folders/h4/77l8l2bd37z5_jkwbw_75nsw0000gn/T/ipykernel_4195/3792770386.py\", line 31>:\n",
      " 31           0 BUILD_LIST               0\n",
      "              2 LOAD_FAST                0 (.0)\n",
      "        >>    4 FOR_ITER                36 (to 42)\n",
      "              6 STORE_DEREF              0 (w)\n",
      "              8 LOAD_GLOBAL              0 (all)\n",
      "             10 LOAD_CLOSURE             1 (item)\n",
      "             12 LOAD_CLOSURE             0 (w)\n",
      "             14 BUILD_TUPLE              2\n",
      "             16 LOAD_CONST               0 (<code object <genexpr> at 0x7ffe14a92450, file \"/var/folders/h4/77l8l2bd37z5_jkwbw_75nsw0000gn/T/ipykernel_4195/3792770386.py\", line 31>)\n",
      "             18 LOAD_CONST               1 ('wordle.<locals>.<listcomp>.<genexpr>')\n",
      "             20 MAKE_FUNCTION            8 (closure)\n",
      "             22 LOAD_DEREF               1 (item)\n",
      "             24 LOAD_CONST               2 (1)\n",
      "             26 BINARY_SUBSCR\n",
      "             28 GET_ITER\n",
      "             30 CALL_FUNCTION            1\n",
      "             32 CALL_FUNCTION            1\n",
      "             34 POP_JUMP_IF_FALSE        4\n",
      "             36 LOAD_DEREF               0 (w)\n",
      "             38 LIST_APPEND              2\n",
      "             40 JUMP_ABSOLUTE            4\n",
      "        >>   42 RETURN_VALUE\n",
      "\n",
      "Disassembly of <code object <genexpr> at 0x7ffe14a92450, file \"/var/folders/h4/77l8l2bd37z5_jkwbw_75nsw0000gn/T/ipykernel_4195/3792770386.py\", line 31>:\n",
      " 31           0 LOAD_FAST                0 (.0)\n",
      "        >>    2 FOR_ITER                22 (to 26)\n",
      "              4 STORE_FAST               1 (value)\n",
      "              6 LOAD_DEREF               1 (w)\n",
      "              8 LOAD_DEREF               0 (item)\n",
      "             10 LOAD_CONST               0 (0)\n",
      "             12 BINARY_SUBSCR\n",
      "             14 BINARY_SUBSCR\n",
      "             16 LOAD_FAST                1 (value)\n",
      "             18 COMPARE_OP               3 (!=)\n",
      "             20 YIELD_VALUE\n",
      "             22 POP_TOP\n",
      "             24 JUMP_ABSOLUTE            2\n",
      "        >>   26 LOAD_CONST               1 (None)\n",
      "             28 RETURN_VALUE\n",
      "\n",
      "Disassembly of <code object <listcomp> at 0x7ffe14a920e0, file \"/var/folders/h4/77l8l2bd37z5_jkwbw_75nsw0000gn/T/ipykernel_4195/3792770386.py\", line 33>:\n",
      " 33           0 BUILD_LIST               0\n",
      "              2 LOAD_FAST                0 (.0)\n",
      "        >>    4 FOR_ITER                30 (to 36)\n",
      "              6 STORE_DEREF              0 (w)\n",
      "              8 LOAD_GLOBAL              0 (all)\n",
      "             10 LOAD_CLOSURE             0 (w)\n",
      "             12 BUILD_TUPLE              1\n",
      "             14 LOAD_CONST               0 (<code object <genexpr> at 0x7ffe14a92030, file \"/var/folders/h4/77l8l2bd37z5_jkwbw_75nsw0000gn/T/ipykernel_4195/3792770386.py\", line 33>)\n",
      "             16 LOAD_CONST               1 ('wordle.<locals>.<listcomp>.<genexpr>')\n",
      "             18 MAKE_FUNCTION            8 (closure)\n",
      "             20 LOAD_DEREF               1 (yellow_letters)\n",
      "             22 GET_ITER\n",
      "             24 CALL_FUNCTION            1\n",
      "             26 CALL_FUNCTION            1\n",
      "             28 POP_JUMP_IF_FALSE        4\n",
      "             30 LOAD_DEREF               0 (w)\n",
      "             32 LIST_APPEND              2\n",
      "             34 JUMP_ABSOLUTE            4\n",
      "        >>   36 RETURN_VALUE\n",
      "\n",
      "Disassembly of <code object <genexpr> at 0x7ffe14a92030, file \"/var/folders/h4/77l8l2bd37z5_jkwbw_75nsw0000gn/T/ipykernel_4195/3792770386.py\", line 33>:\n",
      " 33           0 LOAD_FAST                0 (.0)\n",
      "        >>    2 FOR_ITER                14 (to 18)\n",
      "              4 STORE_FAST               1 (c)\n",
      "              6 LOAD_FAST                1 (c)\n",
      "              8 LOAD_DEREF               0 (w)\n",
      "             10 CONTAINS_OP              0\n",
      "             12 YIELD_VALUE\n",
      "             14 POP_TOP\n",
      "             16 JUMP_ABSOLUTE            2\n",
      "        >>   18 LOAD_CONST               0 (None)\n",
      "             20 RETURN_VALUE\n",
      "None\n"
     ]
    }
   ],
   "source": [
    "import dis\n",
    "print(dis.dis(wordle))"
   ]
  }
 ],
 "metadata": {
  "kernelspec": {
   "display_name": "Python 3 (ipykernel)",
   "language": "python",
   "name": "python3"
  },
  "language_info": {
   "codemirror_mode": {
    "name": "ipython",
    "version": 3
   },
   "file_extension": ".py",
   "mimetype": "text/x-python",
   "name": "python",
   "nbconvert_exporter": "python",
   "pygments_lexer": "ipython3",
   "version": "3.9.7"
  }
 },
 "nbformat": 4,
 "nbformat_minor": 5
}
